Workbook

Sheet Прогнозы
B2: Исходные данные по прогнозам | D2: https://www.economy.gov.ru/material/directions/makroec/prognozy_socialno_ekonomicheskogo_razvitiya/prognoz_socialno_ekonomicheskogo_razvitiya_rf_na_2026_god_i_na_planovyy_period_2027_i_2028_godov.html
B3: прогнозы Минэкономразвития
C4: 2022 | D4: =C4+1 -> 2023 | E4: =D4+1 -> 2024 | F4: =E4+1 -> 2025 | G4: =F4+1 -> 2026 | H4: 2027 | I4: 2028
C5: отчет | F5: прогноз
B6: Темп роста ВВП
B7: базовый | C7: 0.979 | D7: 1.028295 | E7: 1.043 | F7: 1.0103 | G7: 1.01312 | H7: 1.0282 | I7: 1.0251
B8: консервативный | C8: 0.979 | D8: 1.026 | E8: 1.043 | F8: 1.0103 | G8: 1.008 | H8: 1.015 | I8: 1.019
C11: 2025 | D11: 2026 | E11: 2027 | F11: 2028 | G11: средние на 2025 | H11: средние на 2026
B12: Ключевая ставка, в среднем за год, % годовых
B13: базовый сценарий | C13: 6,5–7,0 | D13: 4,0-5,0 | E13: 4 | F13: 4 | G13: =AVERAGE(6.5%,7%) -> 0.0675 | H13: =AVERAGE(4.5%,5%) -> 0.0475
B14: ускоренная адаптация | C14: 6,5–7,0 | D14: 3,5–4,5 | E14: 4 | F14: 4 | G14: =AVERAGE(6.5%,7%) -> 0.0675 | H14: =AVERAGE(3.5%,4.5%) -> 0.04
B15: глобальный кризис | C15: 6,5–7,0 | D15: 10,5–12,5 | E15: 8,0–10,0 | F15: 4,0-4,5 | G15: =AVERAGE(6.5%,7%) -> 0.0675 | H15: =AVERAGE(10.5%,12.5%) -> 0.115
B18: прогнозы ЦБ
C19: 2022 | D19: =C19+1 -> 2023 | E19: =D19+1 -> 2024 | F19: =E19+1 -> 2025 | G19: =F19+1 -> 2026 | H19: =G19+1 -> 2027 | I19: =H19+1 -> 2028 | J19: средние на 2024 | K19: средние на 2025 | L19: средние на 2026
B20: Ключевая ставка, в среднем за год, % годовых
B21: базовый сценарий | C21: 0.106 | D21: 0.099 | E21: 0.175 | F21: 18,8%-19,6% | G21: 12%-13% | H21: 7,5%-8,5% | I21: 7,5%-8,5% | J21: =AVERAGE(17.5%) -> 0.175 | K21: =AVERAGE(18.8%,19.6%) -> 0.192 | L21: =AVERAGE(12%,13%) -> 0.125
B22: ускоренная адаптация | C22: 0.106 | D22: 0.099 | E22: 0.175 | F22: 18,8%-19,6% | G22: 10,5%-11,5% | H22: 7,5%-8,5% | I22: 7,5%-8,5% | J22: =AVERAGE(17.5%) -> 0.175 | K22: =AVERAGE(18.8%,19.6%) -> 0.192 | L22: =AVERAGE(10.5%,11.5%) -> 0.11
B23: глобальный кризис | C23: 0.106 | D23: 0.099 | E23: 0.175 | F23: 18,8%-19,6% | G23: 16%-18% | H23: 18%-20% | I23: 10%-11% | J23: =AVERAGE(17.5%) -> 0.175 | K23: =AVERAGE(18.8%,19.6%) -> 0.192 | L23: =AVERAGE(16%,18%) -> 0.17
B25: Взвешенное значение прогноза в соответствии с базовым и консервативным сценарием
F26: 2026 год
B27: Сценарий | C27: Вес сценария* | D27: Темп роста ВВП | E27: Ключевая ставка | F27: Темп роста ВВП | G27: Ключевая ставка | H27: Инфляция, %
B28: Базовый сценарий | C28: 0.5 | D28: =F7 -> 1.0103 | E28: =K21 -> 0.192 | F28: =G7 -> 1.01312 | G28: 0.125 | H28: =H13 -> 0.0475
B29: Консервативный сценарий | C29: 0.5 | D29: =F8 -> 1.0103 | E29: =K22 -> 0.192 | F29: =G8 -> 1.008 | G29: =L23 -> 0.17 | H29: =H15 -> 0.115
B30: Итого | C30: =SUM(C28:C29) -> 1 | D30: =C28*D28+C29*D29 -> 1.0103 | E30: =C28*E28+C29*E29 -> 0.192 | F30: =C28*F28+C29*F29 -> 1.01056 | G30: =C28*G28+C29*G29 -> 0.1475 | H30: =C28*H28+C29*H29 -> 0.08125
B31: *веса сценариев определяются экспертно на основе доступно информации о прогнозах аналитиков и экспертов о развитии экономики
B33: С учетом того что с 1 января по 27 июля 2025 года средняя ключевая ставка была равна 20,8%, с 28 июля до конца 2025 года средняя ключевая ставка прогнозируется в диапазоне 16,3 – 18,0%. Дополнительная информация о формате прогноза ключевой ставки представлена в методологическом комментарии

Sheet Данные для расчета NPL>

Sheet Total_before_2019
A1: Задолженность по кредитам, предоставленным юридическим лицам - резидентам и индивидуальным предпринимателям в рублях, по видам экономической деятельности и отдельным направлениям использования средств
A2: млн.руб.
A4: Отчетная дата | B4: Задолженность по кредитам
B5: Всего | C5: добыча полезных ископаемых | D5: из них: | E5: обрабатывающие производства | F5: из них: | Q5: производство и распределение электроэнергии, газа и воды | R5: сельское хозяйство, охота и лесное хозяйство | S5: из них: | T5: строительство | U5: из них: | V5: транспорт и связь | W5: из них: | X5: оптовая и розничная торговля; ремонт автотранспортных средств, мотоциклов, бытовых изделий и предметов личного пользования | Y5: операции с недвижимым имуществом, аренда и предоставление услуг | Z5: прочие виды деятельности | AA5: на завершение расчетов
D6: добыча топливно-энергетических полезных ископаемых | F6: производство пищевых продуктов, включая напитки, и табака | G6: обработка древесины и производство изделий из дерева | H6: целлюлозно-бумажное производство; издательская и полиграфическая деятельность | I6: производство кокса, нефтепродуктов и ядерных материалов | J6: химическое производство | K6: производство прочих неметаллических минеральных продуктов | L6: металлургическое производство и производство готовых металлических изделий | M6: производство машин и оборудования | N6: из них: | O6: производство транспортных средств и оборудования | P6: из них: | S6: сельское хозяйство, охота и предоставление услуг в этих областях | U6: строительство зданий и сооружений | W6: деятельность воздушного транспорта, подчиняющегося и не подчиняющегося расписанию
N7: производство машин и оборудования для сельского и лесного хозяйства | P7: производство автомобилей
A8: 39904 | B8: 9174235 | C8: 320171 | D8: 187222 | E8: 1733933 | F8: 368981 | G8: 42652 | H8: 43351 | I8: 39265 | J8: 98250 | K8: 125014 | L8: 324766 | M8: 163275 | N8: 7736 | O8: 222459 | P8: 88279 | Q8: 284201 | R8: 638945 | S8: 577601 | T8: 874494 | U8: 610188 | V8: 503467 | W8: 37657 | X8: 2310931 | Y8: 863857 | Z8: 1525409 | AA8: 118828
A9: 39934 | B9: 9122247 | C9: 287708 | D9: 155815 | E9: 1731607 | F9: 371464 | G9: 42804 | H9: 44139 | I9: 36657 | J9: 93092 | K9: 126174 | L9: 329013 | M9: 165461 | N9: 8273 | O9: 221302 | P9: 93582 | Q9: 279353 | R9: 653357 | S9: 599345 | T9: 875360 | U9: 608251 | V9: 514757 | W9: 39564 | X9: 2282204 | Y9: 859101 | Z9: 1523302 | AA9: 115499
A10: 39965 | B10: 9140944 | C10: 287192 | D10: 154657 | E10: 1723134 | F10: 366692 | G10: 42963 | H10: 43834 | I10: 39665 | J10: 91705 | K10: 127129 | L10: 326387 | M10: 169666 | N10: 9283 | O10: 222388 | P10: 95368 | Q10: 294985 | R10: 665906 | S10: 608226 | T10: 880671 | U10: 618918 | V10: 537458 | W10: 39376 | X10: 2266891 | Y10: 875832 | Z10: 1501179 | AA10: 107697
A11: 39995 | B11: 9063617 | C11: 251739 | D11: 118066 | E11: 1711269 | F11: 369759 | G11: 41549 | H11: 42983 | I11: 42335 | J11: 90873 | K11: 127288 | L11: 316522 | M11: 168746 | N11: 8845 | O11: 218028 | P11: 86780 | Q11: 298478 | R11: 673918 | S11: 615667 | T11: 865198 | U11: 601647 | V11: 493562 | W11: 37639 | X11: 2271800 | Y11: 891203 | Z11: 1506270 | AA11: 100180
A12: 40026 | B12: 9043354 | C12: 251191 | D12: 117767 | E12: 1734748 | F12: 373272 | G12: 42024 | H12: 44022 | I12: 45209 | J12: 89968 | K12: 128835 | L12: 323904 | M12: 177019 | N12: 9526 | O12: 217063 | P12: 85970 | Q12: 312460 | R12: 689072 | S12: 629965 | T12: 860139 | U12: 599553 | V12: 423558 | W12: 38665 | X12: 2284861 | Y12: 916023 | Z12: 1474502 | AA12: 96800
A13: 40057 | B13: 9105925 | C13: 239093 | D13: 112253 | E13: 1746709 | F13: 378728 | G13: 42671 | H13: 47245 | I13: 46048 | J13: 90905 | K13: 131836 | L13: 317385 | M13: 180968 | N13: 9444 | O13: 218513 | P13: 87565 | Q13: 329366 | R13: 703607 | S13: 642244 | T13: 869285 | U13: 610322 | V13: 392728 | W13: 39037 | X13: 2303762 | Y13: 936634 | Z13: 1487114 | AA13: 97628
A14: 40087 | B14: 9225599 | C14: 230715 | D14: 110902 | E14: 1766979 | F14: 383933 | G14: 42868 | H14: 40919 | I14: 49972 | J14: 92554 | K14: 133796 | L14: 317660 | M14: 182278 | N14: 9077 | O14: 223333 | P14: 88276 | Q14: 334731 | R14: 721646 | S14: 653423 | T14: 900119 | U14: 635416 | V14: 423321 | W14: 38393 | X14: 2319128 | Y14: 921867 | Z14: 1509002 | AA14: 98091
A15: 40118 | B15: 9184017 | C15: 221693 | D15: 107099 | E15: 1795728 | F15: 395452 | G15: 42349 | H15: 41049 | I15: 55051 | J15: 95799 | K15: 134053 | L15: 321413 | M15: 179486 | N15: 9154 | O15: 226146 | P15: 89290 | Q15: 342336 | R15: 724996 | S15: 657616 | T15: 898972 | U15: 636770 | V15: 401775 | W15: 39343 | X15: 2314061 | Y15: 920839 | Z15: 1461376 | AA15: 102240
A16: 40148 | B16: 9124732 | C16: 211451 | D16: 105363 | E16: 1762943 | F16: 397973 | G16: 41354 | H16: 40326 | I16: 46495 | J16: 96770 | K16: 132496 | L16: 294510 | M16: 183063 | N16: 9986 | O16: 228196 | P16: 89131 | Q16: 351970 | R16: 729819 | S16: 661576 | T16: 901361 | U16: 642140 | V16: 412685 | W16: 39677 | X16: 2309790 | Y16: 912603 | Z16: 1428003 | AA16: 104107
A17: 40179 | B17: 9109136 | C17: 206559 | D17: 100901 | E17: 1753930 | F17: 406192 | G17: 42062 | H17: 39473 | I17: 48718 | J17: 99208 | K17: 135264 | L17: 281620 | M17: 184587 | N17: 9607 | O17: 216260 | P17: 91504 | Q17: 361907 | R17: 739885 | S17: 675850 | T17: 868071 | U17: 625285 | V17: 420986 | W17: 43141 | X17: 2272813 | Y17: 918279 | Z17: 1484781 | AA17: 81925
A18: 40210 | B18: 9064932 | C18: 192262 | D18: 97244 | E18: 1778103 | F18: 412624 | G18: 43139 | H18: 39668 | I18: 47477 | J18: 108753 | K18: 131024 | L18: 292339 | M18: 178320 | N18: 9284 | O18: 246460 | P18: 90788 | Q18: 369335 | R18: 737334 | S18: 678866 | T18: 869497 | U18: 630623 | V18: 430309 | W18: 48034 | X18: 2167405 | Y18: 918553 | Z18: 1494424 | AA18: 107710
A19: 40238 | B19: 9080461 | C19: 164492 | D19: 96381 | E19: 1804206 | F19: 414697 | G19: 44916 | H19: 40002 | I19: 44383 | J19: 116955 | K19: 129925 | L19: 299008 | M19: 185264 | N19: 9420 | O19: 247002 | P19: 89756 | Q19: 369611 | R19: 742030 | S19: 684333 | T19: 878137 | U19: 627501 | V19: 423356 | W19: 59104 | X19: 2183928 | Y19: 923200 | Z19: 1483247 | AA19: 108254
... A125: 43466 | B125: 25760819 | C125: 1732788 | D125: 1531816 | E125: 4922293 | F125: 803120 | G125: 95025 | H125: 143024 | I125: 324429 | J125: 370894 | K125: 340671 | L125: 853310 | M125: 341409 | N125: 8368 | O125: 1128358 | P125: 200632 | Q125: 1317111 | R125: 1881368 | S125: 1853036 | T125: 1399236 | U125: 1174401 | V125: 1997672 | W125: 125900 | X125: 3864086 | Y125: 3746886 | Z125: 4648662 | AA125: 250718

Sheet Non-performing_before_2019
A1: Просроченная задолженность по кредитам, предоставленным юридическим лицам - резидентам и индивидуальным предпринимателям в рублях, по видам экономической деятельности и отдельным направлениям использования средств | Q1: Источник:
A2: млн.руб. | Q2: Просроченная задолженность по кредитам, предоставленным юридическим лицам - резидентам и индивидуальным предпринимателям в рублях, по видам экономической деятельности и отдельным направлениям использования средств | Банк России (cbr.ru)
Q3: https://cbr.ru/vfs/statistics/BankSector/Loans_to_corporations/01_02_A_Debt_corp_by_activity.xlsx
A4: Отчетная дата | B4: Просроченная задолженность по кредитам
B5: Всего | C5: добыча полезных ископаемых | D5: из них: | E5: обрабатывающие производства | F5: из них: | Q5: производство и распределение электроэнергии, газа и воды | R5: сельское хозяйство, охота и лесное хозяйство | S5: из них: | T5: строительство | U5: из них: | V5: транспорт и связь | W5: из них: | X5: оптовая и розничная торговля; ремонт автотранспортных средств, мотоциклов, бытовых изделий и предметов личного пользования | Y5: операции с недвижимым имуществом, аренда и предоставление услуг | Z5: прочие виды деятельности | AA5: на завершение расчетов
D6: добыча топливно-энергетических полезных ископаемых | F6: производство пищевых продуктов, включая напитки, и табака | G6: обработка древесины и производство изделий из дерева | H6: целлюлозно-бумажное производство; издательская и полиграфическая деятельность | I6: производство кокса, нефтепродуктов и ядерных материалов | J6: химическое производство | K6: производство прочих неметаллических минеральных продуктов | L6: металлургическое производство и производство готовых металлических изделий | M6: производство машин и оборудования | N6: из них: | O6: производство транспортных средств и оборудования | P6: из них: | S6: сельское хозяйство, охота и предоставление услуг в этих областях | U6: строительство зданий и сооружений | W6: деятельность воздушного транспорта, подчиняющегося и не подчиняющегося расписанию
N7: производство машин и оборудования для сельского и лесного хозяйства | P7: производство автомобилей
A8: 39904 | B8: 346769 | C8: 3084 | D8: 1813 | E8: 69830 | F8: 23171 | G8: 3464 | H8: 1861 | I8: 381 | J8: 2475 | K8: 2758 | L8: 4990 | M8: 4112 | N8: 84 | O8: 6063 | P8: 4362 | Q8: 3737 | R8: 15256 | S8: 10854 | T8: 43447 | U8: 33272 | V8: 10279 | W8: 3181 | X8: 138637 | Y8: 18999 | Z8: 30438 | AA8: 13062
A9: 39934 | B9: 380065 | C9: 4032 | D9: 1871 | E9: 74435 | F9: 24133 | G9: 3711 | H9: 1999 | I9: 672 | J9: 2615 | K9: 2728 | L9: 6294 | M9: 3428 | N9: 352 | O9: 6549 | P9: 4486 | Q9: 3685 | R9: 15318 | S9: 12145 | T9: 45735 | U9: 35817 | V9: 11171 | W9: 2853 | X9: 153720 | Y9: 23304 | Z9: 34319 | AA9: 14346
A10: 39965 | B10: 409667 | C10: 3235 | D10: 1967 | E10: 80603 | F10: 24110 | G10: 3984 | H10: 2156 | I10: 672 | J10: 2989 | K10: 2782 | L10: 6614 | M10: 4354 | N10: 564 | O10: 6713 | P10: 4900 | Q10: 4364 | R10: 16065 | S10: 12997 | T10: 54593 | U10: 43278 | V10: 11626 | W10: 3251 | X10: 164652 | Y10: 25073 | Z10: 34600 | AA10: 14857
A11: 39995 | B11: 428450 | C11: 5346 | D11: 2732 | E11: 89104 | F11: 24647 | G11: 4178 | H11: 2046 | I11: 1192 | J11: 1587 | K11: 3863 | L11: 8486 | M11: 4989 | N11: 712 | O11: 9563 | P11: 6221 | Q11: 5646 | R11: 16871 | S11: 13457 | T11: 43162 | U11: 31523 | V11: 12542 | W11: 3552 | X11: 174102 | Y11: 27509 | Z11: 40487 | AA11: 13680
A12: 40026 | B12: 478269 | C12: 7519 | D12: 2067 | E12: 93343 | F12: 22821 | G12: 5309 | H12: 3447 | I12: 2056 | J12: 1980 | K12: 3972 | L12: 7568 | M12: 7805 | N12: 615 | O12: 10877 | P12: 7550 | Q12: 5656 | R12: 17591 | S12: 14571 | T12: 45867 | U12: 32796 | V12: 16209 | W12: 4738 | X12: 196035 | Y12: 41231 | Z12: 40969 | AA12: 13850
A13: 40057 | B13: 524767 | C13: 5405 | D13: 2323 | E13: 111160 | F13: 24682 | G13: 5780 | H13: 3780 | I13: 2056 | J13: 2289 | K13: 4426 | L13: 13342 | M13: 8578 | N13: 599 | O13: 13448 | P13: 10864 | Q13: 6114 | R13: 18637 | S13: 15530 | T13: 48143 | U13: 34078 | V13: 16031 | W13: 4743 | X13: 215448 | Y13: 44715 | Z13: 44788 | AA13: 14326
A14: 40087 | B14: 549154 | C14: 5410 | D14: 2204 | E14: 107115 | F14: 21908 | G14: 6538 | H14: 3874 | I14: 2055 | J14: 2868 | K14: 4705 | L14: 10048 | M14: 7939 | N14: 151 | O14: 16536 | P14: 11783 | Q14: 6958 | R14: 20648 | S14: 17406 | T14: 53679 | U14: 39273 | V14: 15433 | W14: 3829 | X14: 228604 | Y14: 42021 | Z14: 54600 | AA14: 14687
A15: 40118 | B15: 575537 | C15: 6241 | D15: 3053 | E15: 121681 | F15: 23559 | G15: 6355 | H15: 4001 | I15: 2194 | J15: 4283 | K15: 4155 | L15: 15859 | M15: 8460 | N15: 166 | O15: 17840 | P15: 11880 | Q15: 7499 | R15: 23559 | S15: 20017 | T15: 56594 | U15: 40352 | V15: 17421 | W15: 6063 | X15: 234969 | Y15: 43191 | Z15: 49602 | AA15: 14781
A16: 40148 | B16: 607313 | C16: 6334 | D16: 3093 | E16: 130482 | F16: 24890 | G16: 6695 | H16: 4063 | I16: 2192 | J16: 4802 | K16: 4772 | L16: 13276 | M16: 11336 | N16: 196 | O16: 20247 | P16: 14424 | Q16: 14114 | R16: 25529 | S16: 21855 | T16: 58669 | U16: 41263 | V16: 18612 | W16: 6447 | X16: 242289 | Y16: 44540 | Z16: 52101 | AA16: 14645
A17: 40179 | B17: 601582 | C17: 5286 | D17: 2753 | E17: 122013 | F17: 23656 | G17: 6516 | H17: 3980 | I17: 2250 | J17: 4935 | K17: 4811 | L17: 14173 | M17: 8775 | N17: 265 | O17: 18835 | P17: 14584 | Q17: 14104 | R17: 26635 | S17: 23128 | T17: 58749 | U17: 41033 | V17: 18822 | W17: 5648 | X17: 238840 | Y17: 40643 | Z17: 62312 | AA17: 14178
A18: 40210 | B18: 595048 | C18: 3613 | D18: 1091 | E18: 133672 | F18: 25816 | G18: 6766 | H18: 4200 | I18: 3379 | J18: 4967 | K18: 5061 | L18: 16680 | M18: 7975 | N18: 470 | O18: 26378 | P18: 14566 | Q18: 14122 | R18: 27614 | S18: 24081 | T18: 59879 | U18: 41044 | V18: 19245 | W18: 5504 | X18: 230011 | Y18: 43858 | Z18: 49613 | AA18: 13421
A19: 40238 | B19: 609184 | C19: 4933 | D19: 2410 | E19: 130515 | F19: 28201 | G19: 7621 | H19: 4200 | I19: 3430 | J19: 3688 | K19: 5309 | L19: 17158 | M19: 8213 | N19: 372 | O19: 19586 | P19: 14554 | Q19: 14152 | R19: 28731 | S19: 25093 | T19: 61215 | U19: 42946 | V19: 19161 | W19: 5153 | X19: 239198 | Y19: 44874 | Z19: 52571 | AA19: 13834
... A125: 43466 | B125: 1899307 | C125: 23235 | D125: 4805 | E125: 331550 | F125: 101334 | G125: 15614 | H125: 7360 | I125: 9768 | J125: 14713 | K125: 60278 | L125: 45091 | M125: 18414 | N125: 320 | O125: 12837 | P125: 5210 | Q125: 20213 | R125: 157914 | S125: 148758 | T125: 287294 | U125: 221789 | V125: 38232 | W125: 10313 | X125: 448945 | Y125: 322240 | Z125: 257081 | AA125: 12603

Sheet Total_after_2019
A1: Виды экономической деятельности и отдельные направления использования средств | B1: ВСЕГО | C1: добыча полезных ископаемых, из них: | D1: добыча топливно-энергетических полезных ископаемых | E1: обрабатывающие производства, из них: | F1: производство пищевых продуктов, включая напитки, и табака | G1: обработка древесины и производство изделий из дерева | H1: целлюлозно-бумажное производство, издательская и полиграфическая деятельность | I1: производство кокса, нефтепродуктов и ядерных материалов | J1: химическое производство | K1: производство прочих неметаллических минеральных продуктов | L1: металлургическое производство и производство готовых металлических изделий | M1: производство машин и оборудования, из них: | N1: производство машин и оборудования для сельского и лесного хозяйства | O1: производство транспортных средств и оборудования, из них: | P1: производство автомобилей | Q1: производство и распределение электроэнергии, газа и воды | R1: сельское хозяйство, охота и лесное хозяйство, из них: | S1: сельское хозяйство, охота и предоставление услуг в этих областях | T1: строительство, из них: | U1: строительство зданий и сооружений | V1: транспорт и связь, из них: | W1: деятельность воздушного транспорта, подчиняющегося и не подчиняющегося расписанию | X1: оптовая и розничная торговля, ремонт автотранспортных средств, мотоциклов, бытовых изделий и предметов личного пользования | Y1: операции с недвижимым имуществом, аренда и предоставление услуг | Z1: прочие виды деятельности | AA1: на завершение расчетов | AB1: Источник: | AC1: https://cbr.ru/vfs/statistics/BankSector/Loans_to_corporations/01_02_A_Debt_corp_by_activity.xlsx
A2: 43497 | B2: 25728662 | C2: ='Non-performing_after_2019'!B2 -> 1949294 | D2: =C2/B2 -> 0.07576352 | E2: 6082270 | F2: 904809 | G2: 92112 | H2: 165875 | I2: 1136171 | J2: 356893 | K2: 346845 | L2: 840995 | M2: 503170 | N2: 9043 | O2: 1188152 | P2: 204497 | Q2: 1218916 | R2: 1725294 | S2: 1710755 | T2: 1063041 | U2: 939923 | V2: 1771028 | W2: 114787 | X2: 3681859 | Y2: 3874280 | Z2: 5078084 | AA2: 274024
A3: 43525 | B3: 25885238 | C3: ='Non-performing_after_2019'!B3 -> 2050020 | D3: =C3/B3 -> 0.07919649 | E3: 6137454 | F3: 911433 | G3: 92536 | H3: 173185 | I3: 1131661 | J3: 356343 | K3: 364350 | L3: 841707 | M3: 510318 | N3: 10265 | O3: 1203206 | P3: 211265 | Q3: 1207717 | R3: 1746871 | S3: 1719165 | T3: 1087213 | U3: 966809 | V3: 1805037 | W3: 114026 | X3: 3678621 | Y3: 3915409 | Z3: 5040035 | AA3: 293369
A4: 43556 | B4: 26209480 | C4: ='Non-performing_after_2019'!B4 -> 2039376 | D4: =C4/B4 -> 0.077810624 | E4: 6138053 | F4: 924484 | G4: 94497 | H4: 183422 | I4: 1126135 | J4: 356349 | K4: 368798 | L4: 855330 | M4: 503786 | N4: 12448 | O4: 1175264 | P4: 185192 | Q4: 1180787 | R4: 1800908 | S4: 1773229 | T4: 1108528 | U4: 986458 | V4: 1841668 | W4: 114186 | X4: 3747668 | Y4: 3936643 | Z4: 5163325 | AA4: 305200
A5: 43586 | B5: 26433363 | C5: ='Non-performing_after_2019'!B5 -> 2126326 | D5: =C5/B5 -> 0.080440994 | E5: 6295855 | F5: 947175 | G5: 95185 | H5: 186568 | I5: 1119811 | J5: 370422 | K5: 370694 | L5: 916808 | M5: 489212 | N5: 13945 | O5: 1174900 | P5: 222525 | Q5: 1182415 | R5: 1842789 | S5: 1814797 | T5: 1131064 | U5: 1006435 | V5: 1818916 | W5: 114077 | X5: 3747493 | Y5: 3958059 | Z5: 5131499 | AA5: 313063
A6: 43617 | B6: 26513261 | C6: ='Non-performing_after_2019'!B6 -> 2154522 | D6: =C6/B6 -> 0.081262052 | E6: 6277996 | F6: 926671 | G6: 93959 | H6: 187665 | I6: 1097271 | J6: 372012 | K6: 369268 | L6: 915341 | M6: 500264 | N6: 12503 | O6: 1183688 | P6: 223392 | Q6: 1183870 | R6: 1872347 | S6: 1845029 | T6: 1146542 | U6: 1020534 | V6: 1797562 | W6: 110683 | X6: 3740684 | Y6: 3977484 | Z6: 5201456 | AA6: 301725
A7: 43647 | B7: 26675170 | C7: ='Non-performing_after_2019'!B7 -> 2167683 | D7: =C7/B7 -> 0.0812622 | E7: 6265019 | F7: 918307 | G7: 94419 | H7: 188107 | I7: 1093157 | J7: 374407 | K7: 365544 | L7: 931478 | M7: 502653 | N7: 9574 | O7: 1154792 | P7: 188702 | Q7: 1203128 | R7: 1901775 | S7: 1874127 | T7: 1169732 | U7: 1040557 | V7: 1804384 | W7: 112582 | X7: 3735928 | Y7: 3996904 | Z7: 5296277 | AA7: 290411
A8: 43678 | B8: 26849438 | C8: ='Non-performing_after_2019'!B8 -> 2205926 | D8: =C8/B8 -> 0.082159113 | E8: 6310098 | F8: 910878 | G8: 93542 | H8: 191584 | I8: 1089861 | J8: 387826 | K8: 363349 | L8: 961326 | M8: 514920 | N8: 8643 | O8: 1143172 | P8: 187178 | Q8: 1216249 | R8: 1929686 | S8: 1902553 | T8: 1203431 | U8: 1072594 | V8: 1795332 | W8: 110328 | X8: 3717436 | Y8: 4040166 | Z8: 5354908 | AA8: 282084
A9: 43709 | B9: 27110459 | C9: ='Non-performing_after_2019'!B9 -> 2206565 | D9: =C9/B9 -> 0.08139165 | E9: 6379661 | F9: 923369 | G9: 91855 | H9: 193144 | I9: 1137251 | J9: 389334 | K9: 357052 | L9: 941930 | M9: 521525 | N9: 8281 | O9: 1162792 | P9: 195452 | Q9: 1244014 | R9: 1933293 | S9: 1906316 | T9: 1231981 | U9: 1098769 | V9: 1798274 | W9: 108325 | X9: 3723725 | Y9: 4132575 | Z9: 5397768 | AA9: 280701
A10: 43739 | B10: 27256839 | C10: ='Non-performing_after_2019'!B10 -> 2227953 | D10: =C10/B10 -> 0.081739229 | E10: 6453188 | F10: 964124 | G10: 91959 | H10: 195581 | I10: 1145350 | J10: 390091 | K10: 355930 | L10: 928970 | M10: 534200 | N10: 8161 | O10: 1179565 | P10: 187045 | Q10: 1240908 | R10: 1946462 | S10: 1919280 | T10: 1255454 | U10: 1116876 | V10: 1831630 | W10: 109237 | X10: 3696967 | Y10: 4155038 | Z10: 5402378 | AA10: 286714
A11: 43770 | B11: 27466530 | C11: ='Non-performing_after_2019'!B11 -> 2191242 | D11: =C11/B11 -> 0.079778625 | E11: 6437282 | F11: 988232 | G11: 93045 | H11: 205332 | I11: 1047604 | J11: 396920 | K11: 351756 | L11: 989071 | M11: 547323 | N11: 7999 | O11: 1183288 | P11: 175310 | Q11: 1241427 | R11: 1915876 | S11: 1888522 | T11: 1265871 | U11: 1127319 | V11: 1835998 | W11: 116030 | X11: 3789615 | Y11: 4224697 | Z11: 5452059 | AA11: 290805
A12: 43800 | B12: 27672879 | C12: ='Non-performing_after_2019'!B12 -> 2126786 | D12: =C12/B12 -> 0.076854526 | E12: 6307192 | F12: 1001411 | G12: 94685 | H12: 224027 | I12: 971323 | J12: 390820 | K12: 321577 | L12: 908927 | M12: 564924 | N12: 8472 | O12: 1188926 | P12: 174759 | Q12: 1252643 | R12: 1976858 | S12: 1949218 | T12: 1281089 | U12: 1146693 | V12: 1817133 | W12: 114161 | X12: 3786203 | Y12: 4288569 | Z12: 5663296 | AA12: 294780
A13: 43831 | B13: 27586340 | C13: ='Non-performing_after_2019'!B13 -> 2084839 | D13: =C13/B13 -> 0.075575049 | E13: 6184484 | F13: 991988 | G13: 94924 | H13: 225830 | I13: 1027691 | J13: 390898 | K13: 309439 | L13: 898487 | M13: 508971 | N13: 8621 | O13: 1119549 | P13: 171242 | Q13: 1284964 | R13: 1995510 | S13: 1967617 | T13: 1218697 | U13: 1082759 | V13: 1832529 | W13: 118005 | X13: 3549400 | Y13: 4331135 | Z13: 5879388 | AA13: 299605
... A81: 45901 | B81: 79684852 | C81: ='Non-performing_after_2019'!B81 -> 2827694 | D81: =C81/B81 -> 0.035485967 | E81: 20528051 | F81: 1858716 | G81: 161284 | H81: 513811 | I81: 4183000 | J81: 4542871 | K81: 378771 | L81: 3306264 | M81: 1144637 | N81: 41769 | O81: 2677955 | P81: 442119 | Q81: 1666254 | R81: 3000122 | S81: 2961303 | T81: 5009025 | U81: 4640703 | V81: 4635432 | W81: 114325 | X81: 7398255 | Y81: 16391412 | Z81: 15313700 | AA81: 438517

Sheet Non-performing_after_2019
A1: Виды экономической деятельности и отдельные направления использования средств | B1: ВСЕГО | C1: добыча полезных ископаемых, из них: | D1: добыча топливно-энергетических полезных ископаемых | E1: обрабатывающие производства, из них: | F1: производство пищевых продуктов, включая напитки, и табака | G1: обработка древесины и производство изделий из дерева | H1: целлюлозно-бумажное производство, издательская и полиграфическая деятельность | I1: производство кокса, нефтепродуктов и ядерных материалов | J1: химическое производство | K1: производство прочих неметаллических минеральных продуктов | L1: металлургическое производство и производство готовых металлических изделий | M1: производство машин и оборудования, из них: | N1: производство машин и оборудования для сельского и лесного хозяйства | O1: производство транспортных средств и оборудования, из них: | P1: производство автомобилей | Q1: производство и распределение электроэнергии, газа и воды | R1: сельское хозяйство, охота и лесное хозяйство, из них: | S1: сельское хозяйство, охота и предоставление услуг в этих областях | T1: строительство, из них: | U1: строительство зданий и сооружений | V1: транспорт и связь, из них: | W1: деятельность воздушного транспорта, подчиняющегося и не подчиняющегося расписанию | X1: оптовая и розничная торговля, ремонт автотранспортных средств, мотоциклов, бытовых изделий и предметов личного пользования | Y1: операции с недвижимым имуществом, аренда и предоставление услуг | Z1: прочие виды деятельности | AA1: на завершение расчетов | AB1: Источник: | AC1: https://cbr.ru/vfs/statistics/BankSector/Loans_to_corporations/01_02_A_Debt_corp_by_activity.xlsx
A2: 43497 | B2: 1949294 | C2: 8647 | D2: 4559 | E2: 330899 | F2: 101574 | G2: 14484 | H2: 10398 | I2: 10596 | J2: 7246 | K2: 64824 | L2: 47588 | M2: 15007 | N2: 266 | O2: 6547 | P2: 1334 | Q2: 23070 | R2: 159894 | S2: 154522 | T2: 259094 | U2: 228912 | V2: 38647 | W2: 874 | X2: 467236 | Y2: 363712 | Z2: 284633 | AA2: 13461
A3: 43525 | B3: 2050020 | C3: 20790 | D3: 16597 | E3: 353716 | F3: 102703 | G3: 14505 | H3: 10496 | I3: 10347 | J3: 7232 | K3: 77797 | L3: 47035 | M3: 20090 | N3: 262 | O3: 10038 | P3: 1334 | Q3: 22997 | R3: 181058 | S3: 162901 | T3: 260655 | U3: 230837 | V3: 39836 | W3: 892 | X3: 488691 | Y3: 362572 | Z3: 306056 | AA3: 13651
A4: 43556 | B4: 2039376 | C4: 23598 | D4: 19289 | E4: 357362 | F4: 102048 | G4: 20188 | H4: 10376 | I4: 10283 | J4: 7069 | K4: 77754 | L4: 46559 | M4: 20516 | N4: 268 | O4: 9666 | P4: 1333 | Q4: 22939 | R4: 183416 | S4: 165292 | T4: 259655 | U4: 230458 | V4: 41157 | W4: 1104 | X4: 477341 | Y4: 362175 | Z4: 297832 | AA4: 13901
A5: 43586 | B5: 2126326 | C5: 23634 | D5: 19332 | E5: 431309 | F5: 101917 | G5: 22078 | H5: 10299 | I5: 15750 | J5: 7772 | K5: 81781 | L5: 46418 | M5: 21445 | N5: 260 | O5: 10229 | P5: 1357 | Q5: 22977 | R5: 185347 | S5: 167235 | T5: 269132 | U5: 239815 | V5: 38652 | W5: 884 | X5: 479291 | Y5: 365769 | Z5: 296764 | AA5: 13452
A6: 43617 | B6: 2154522 | C6: 23661 | D6: 19388 | E6: 437136 | F6: 102318 | G6: 21776 | H6: 10334 | I6: 21350 | J6: 8182 | K6: 78098 | L6: 48536 | M6: 23320 | N6: 260 | O6: 10286 | P6: 1350 | Q6: 23188 | R6: 184504 | S6: 167127 | T6: 271132 | U6: 241903 | V6: 38511 | W6: 892 | X6: 483565 | Y6: 382384 | Z6: 296643 | AA6: 13798
A7: 43647 | B7: 2167683 | C7: 26943 | D7: 22647 | E7: 439061 | F7: 102065 | G7: 21966 | H7: 10326 | I7: 21364 | J7: 8251 | K7: 77893 | L7: 48718 | M7: 23765 | N7: 260 | O7: 10166 | P7: 1361 | Q7: 23333 | R7: 187754 | S7: 170391 | T7: 269421 | U7: 241142 | V7: 50597 | W7: 901 | X7: 477532 | Y7: 379922 | Z7: 298441 | AA7: 14679
A8: 43678 | B8: 2205926 | C8: 27014 | D8: 22719 | E8: 455711 | F8: 104504 | G8: 22060 | H8: 11107 | I8: 23276 | J8: 8852 | K8: 80576 | L8: 48514 | M8: 24634 | N8: 259 | O8: 17535 | P8: 8793 | Q8: 24487 | R8: 189616 | S8: 172225 | T8: 273469 | U8: 244682 | V8: 50800 | W8: 882 | X8: 479987 | Y8: 390741 | Z8: 298819 | AA8: 15282
A9: 43709 | B9: 2206565 | C9: 30318 | D9: 22646 | E9: 466994 | F9: 101903 | G9: 27300 | H9: 10417 | I9: 23287 | J9: 8847 | K9: 91173 | L9: 49122 | M9: 22881 | N9: 259 | O9: 17463 | P9: 8792 | Q9: 24392 | R9: 186414 | S9: 169058 | T9: 278149 | U9: 249203 | V9: 50321 | W9: 864 | X9: 466324 | Y9: 388023 | Z9: 300397 | AA9: 15235
A10: 43739 | B10: 2227953 | C10: 31925 | D10: 24279 | E10: 499394 | F10: 100086 | G10: 27655 | H10: 10452 | I10: 36245 | J10: 8828 | K10: 110573 | L10: 49289 | M10: 23427 | N10: 259 | O10: 17469 | P10: 8792 | Q10: 23220 | R10: 183405 | S10: 166077 | T10: 278322 | U10: 249870 | V10: 53326 | W10: 869 | X10: 455936 | Y10: 391023 | Z10: 296525 | AA10: 14875
A11: 43770 | B11: 2191242 | C11: 34258 | D11: 26832 | E11: 468285 | F11: 100412 | G11: 27792 | H11: 10491 | I11: 36255 | J11: 8713 | K11: 78911 | L11: 49117 | M11: 23702 | N11: 259 | O11: 17719 | P11: 8787 | Q11: 23254 | R11: 182091 | S11: 164773 | T11: 276283 | U11: 248505 | V11: 54208 | W11: 845 | X11: 458002 | Y11: 388901 | Z11: 291142 | AA11: 14819
A12: 43800 | B12: 2126786 | C12: 35379 | D12: 28238 | E12: 468289 | F12: 100246 | G12: 27802 | H12: 10495 | I12: 37035 | J12: 8628 | K12: 78912 | L12: 48866 | M12: 23984 | N12: 266 | O12: 17870 | P12: 8805 | Q12: 21150 | R12: 180772 | S12: 163454 | T12: 272114 | U12: 247098 | V12: 51880 | W12: 845 | X12: 432770 | Y12: 382099 | Z12: 267332 | AA12: 15001
A13: 43831 | B13: 2084839 | C13: 36393 | D13: 29406 | E13: 452706 | F13: 101262 | G13: 27848 | H13: 9987 | I13: 31676 | J13: 8596 | K13: 71078 | L13: 48116 | M13: 25097 | N13: 240 | O13: 19080 | P13: 8875 | Q13: 20595 | R13: 176261 | S13: 159067 | T13: 270089 | U13: 243484 | V13: 53056 | W13: 845 | X13: 416722 | Y13: 379320 | Z13: 265356 | AA13: 14340
... A81: 45901 | B81: 2827694 | C81: 76011 | D81: 66831 | E81: 401445 | F81: 49867 | G81: 63992 | H81: 4969 | I81: 36345 | J81: 28177 | K81: 42846 | L81: 38806 | M81: 14561 | N81: 330 | O81: 20358 | P81: 6890 | Q81: 16875 | R81: 91621 | S81: 62583 | T81: 266412 | U81: 228945 | V81: 69103 | W81: 982 | X81: 470256 | Y81: 501856 | Z81: 903770 | AA81: 30343
